waterANN/__init__.py
waterANN/waterquality.py
waterANN-0.0.1.dist-info/LICENSE.txt
waterANN-0.0.1.dist-info/METADATA
waterANN-0.0.1.dist-info/WHEEL
waterANN-0.0.1.dist-info/top_level.txt
waterANN-0.0.1.dist-info/RECORD
