Metadata-Version: 2.1
Name: waterANN
Version: 0.0.1
Summary: XGBoost model for uci bank marketing dataset
Author: AJH
Author-email: 0625dkswjdgn@g.skku.edu
Classifier: Programming Language :: Python :: 3
Classifier: License :: OSI Approved :: MIT License
Classifier: Operating System :: OS Independent
Requires-Python: >=3.6
License-File: LICENSE.txt
